[
  {
    "label": "文学院（含胶东文化研究院）",
    "value": "文学院（含胶东文化研究院）"
  },
  {
    "label": "外国语学院",
    "value": "外国语学院"
  },
  {
    "label": "历史文化学院（含传统文化与现代思想研究院）",
    "value": "历史文化学院（含传统文化与现代思想研究院）"
  },
  {
    "label": "马克思主义学院",
    "value": "马克思主义学院"
  },
  {
    "label": "法学院",
    "value": "法学院"
  },
  {
    "label": "教育科学学院（含问题青少年教育矫正研究院）",
    "value": "教育科学学院（含问题青少年教育矫正研究院）"
  },
  {
    "label": "教师教育学院",
    "value": "教师教育学院"
  },
  {
    "label": "体育学院",
    "value": "体育学院"
  },
  {
    "label": "商学院（含环渤海发展研究院）",
    "value": "商学院（含环渤海发展研究院）"
  },
  {
    "label": "数学与统计科学学院",
    "value": "数学与统计科学学院"
  },
  {
    "label": "物理与光电工程学院",
    "value": "物理与光电工程学院"
  },
  {
    "label": "化学与材料科学学院",
    "value": "化学与材料科学学院"
  },
  {
    "label": "生命科学学院",
    "value": "生命科学学院"
  },
  {
    "label": "资源与环境工程学院（含滨海生态研究院）",
    "value": "资源与环境工程学院（含滨海生态研究院）"
  },
  {
    "label": "交通学院",
    "value": "交通学院"
  },
  {
    "label": "蔚山船舶与海洋学院",
    "value": "蔚山船舶与海洋学院"
  },
  {
    "label": "土木工程学院",
    "value": "土木工程学院"
  },
  {
    "label": "信息与电气工程学院",
    "value": "信息与电气工程学院"
  },
  {
    "label": "食品工程学院",
    "value": "食品工程学院"
  },
  {
    "label": "农学院",
    "value": "农学院"
  },
  {
    "label": "艺术学院",
    "value": "艺术学院"
  },
  {
    "label": "国际教育学院",
    "value": "国际教育学院"
  }

]